database_tools/__init__.py
database_tools/datastores/__init__.py
database_tools/datastores/records.py
database_tools/datastores/signals.py
database_tools/errors.py
database_tools/io/__init__.py
database_tools/io/data.py
database_tools/io/utils.py
database_tools/io/wfdb.py
database_tools/processing/__init__.py
database_tools/processing/cardiac.py
database_tools/processing/detect.py
database_tools/processing/metrics.py
database_tools/processing/modify.py
database_tools/processing/utils.py
database_tools/tools/DataEvaluator.py
database_tools/tools/DataLocator.py
database_tools/tools/__init__.py
database_tools/tools/dataset.py
database_tools/tools/records.py
heartfelt_tools-1.8.0.dist-info/LICENSE
heartfelt_tools-1.8.0.dist-info/METADATA
heartfelt_tools-1.8.0.dist-info/WHEEL
heartfelt_tools-1.8.0.dist-info/RECORD
