Metadata-Version: 2.1
Name: heartfelt-tools
Version: 1.8.0
Summary: Extract and process photoplethysmography and arterial blood pressure data from mimic3-waveforms and vitaldb.
License: MIT
Author: Cameron Johnson
Requires-Python: >=3.9,<3.10
Classifier: License :: OSI Approved :: MIT License
Classifier: Programming Language :: Python :: 3
Classifier: Programming Language :: Python :: 3.9
Requires-Dist: alive-progress (>=3.0.1,<4.0.0)
Requires-Dist: heartpy (>=1.2.7,<2.0.0)
Requires-Dist: neurokit2 (>=0.2.1,<0.3.0)
Requires-Dist: numpy (>=1.23.4,<2.0.0)
Requires-Dist: openpyxl (>=3.0.10,<4.0.0)
Requires-Dist: pandas (>=1.5.1,<2.0.0)
Requires-Dist: plotly (>=5.10.0,<6.0.0)
Requires-Dist: pytest (>=7.2.1,<8.0.0)
Requires-Dist: scikit-learn (>=1.1.2,<2.0.0)
Requires-Dist: scipy (>=1.9.3,<2.0.0)
Requires-Dist: tabulate (>=0.9.0,<0.10.0)
Requires-Dist: tensorflow (==2.9.2)
Requires-Dist: tqdm (>=4.64.1,<5.0.0)
Requires-Dist: vitaldb (>=1.2.10,<2.0.0)
Requires-Dist: wfdb (>=4.0.0,<5.0.0)
